argus_python
