Metadata-Version: 2.1
Name: argus_python
Version: 0.1.1
Summary: A Python Client for the Argus Engine
Home-page: https://github.com/jayjaychukwu/argus-python
Author: Jude Odionye
Author-email: odionye.jude@outlook.com
License: BSD license
Keywords: argus_python
Classifier: Development Status :: 2 - Pre-Alpha
Classifier: Intended Audience :: Developers
Classifier: License :: OSI Approved :: BSD License
Classifier: Natural Language :: English
Classifier: Programming Language :: Python :: 3
Classifier: Programming Language :: Python :: 3.6
Classifier: Programming Language :: Python :: 3.7
Classifier: Programming Language :: Python :: 3.8
Classifier: Programming Language :: Python :: 3.9
Classifier: Programming Language :: Python :: 3.10
Requires-Python: >=3.6
License-File: LICENSE
Requires-Dist: Click>=7.0
